mzStudio/AdjustableProgress.py
mzStudio/AreaWindow.py
mzStudio/BlaisPepCalc.py
mzStudio/BlaisPepCalcSlim_aui.py
mzStudio/BlaisPepCalcSlim_aui2.py
mzStudio/Comet_GUI.py
mzStudio/DatabaseOperations.py
mzStudio/FeatureImport.py
mzStudio/FeaturePopUp.py
mzStudio/FeaturePopUp_new.py
mzStudio/Filter_management.py
mzStudio/HTreeCtrl.py
mzStudio/LabelCoverage.py
mzStudio/ListBank.py
mzStudio/MGrid.py
mzStudio/MSO.py
mzStudio/MascotSearch.py
mzStudio/ModManager.py
mzStudio/ObjectOrganizer.py
mzStudio/Peptigram.py
mzStudio/PopUpWins.py
mzStudio/Progressgauge.py
mzStudio/QueryBuilder.py
mzStudio/RICviewLite.py
mzStudio/RICviewLite_multi.py
mzStudio/Settings.py
mzStudio/SpecBase.py
mzStudio/SpecBase_aui2.py
mzStudio/SpecBase_aui3.py
mzStudio/SpecObject.py
mzStudio/SpecViewLite_build2.py
mzStudio/Tandem_GUI.py
mzStudio/TreeCtrl.py
mzStudio/TreeCtrl2.py
mzStudio/XICObject.py
mzStudio/XICPalette.py
mzStudio/__init__.py
mzStudio/additions.py
mzStudio/autocomplete.py
mzStudio/check_search_type.py
mzStudio/customProcessing.py
mzStudio/dbFrame.py
mzStudio/example_custom_function.py
mzStudio/flatmenu_patched.py
mzStudio/mgf.py
mzStudio/miniCHNOPS.py
mzStudio/mzGUI_standalone.py
mzStudio/mzStudio.py
mzStudio/new_settings.py
mzStudio/t2dv2.py
mzStudio/textSpectrum.py
mzStudio/workbench.py
mzStudio/xls_extensions.py
mzStudio-0.9.9.1.dist-info/DESCRIPTION.rst
mzStudio-0.9.9.1.dist-info/METADATA
mzStudio-0.9.9.1.dist-info/RECORD
mzStudio-0.9.9.1.dist-info/WHEEL
mzStudio-0.9.9.1.dist-info/metadata.json
mzStudio-0.9.9.1.dist-info/top_level.txt
