Metadata-Version: 2.0
Name: mzStudio
Version: 0.9.9.1
Summary: Mass Spectrometry/Proteomics Data Analysis Application
Home-page: http://github.com/BlaisProteomics/mzStudio
Author: Scott Ficarro, William Max Alexander
Author-email: Scott_Ficarro@dfci.harvard.edu
License: UNKNOWN
Platform: UNKNOWN
Requires-Dist: multiplierz
